ChanzhongshuochanJishuLilunTujie/README.md
ChanzhongshuochanJishuLilunTujie/__init__.py
ChanzhongshuochanJishuLilunTujie/__main__.py
ChanzhongshuochanJishuLilunTujie/file.epub
ChanzhongshuochanJishuLilunTujie/index.html
ChanzhongshuochanJishuLilunTujie/css/__init__.py
ChanzhongshuochanJishuLilunTujie/css/annotations.css
ChanzhongshuochanJishuLilunTujie/css/main.css
ChanzhongshuochanJishuLilunTujie/css/normalize.css
ChanzhongshuochanJishuLilunTujie/css/popup.css
ChanzhongshuochanJishuLilunTujie/font/__init__.py
ChanzhongshuochanJishuLilunTujie/font/fontello.eot
ChanzhongshuochanJishuLilunTujie/font/fontello.svg
ChanzhongshuochanJishuLilunTujie/font/fontello.ttf
ChanzhongshuochanJishuLilunTujie/font/fontello.woff
ChanzhongshuochanJishuLilunTujie/img/__init__.py
ChanzhongshuochanJishuLilunTujie/img/annotator-glyph-sprite.png
ChanzhongshuochanJishuLilunTujie/img/annotator-icon-sprite.png
ChanzhongshuochanJishuLilunTujie/img/apple-touch-icon.png
ChanzhongshuochanJishuLilunTujie/img/cancelfullscreen.png
ChanzhongshuochanJishuLilunTujie/img/close.png
ChanzhongshuochanJishuLilunTujie/img/fullscreen.png
ChanzhongshuochanJishuLilunTujie/img/loader.gif
ChanzhongshuochanJishuLilunTujie/img/menu-icon.png
ChanzhongshuochanJishuLilunTujie/img/save.png
ChanzhongshuochanJishuLilunTujie/img/saved.png
ChanzhongshuochanJishuLilunTujie/img/settings-s.png
ChanzhongshuochanJishuLilunTujie/img/settings.png
ChanzhongshuochanJishuLilunTujie/img/star.png
ChanzhongshuochanJishuLilunTujie/js/__init__.py
ChanzhongshuochanJishuLilunTujie/js/epub.js
ChanzhongshuochanJishuLilunTujie/js/epub.min.js
ChanzhongshuochanJishuLilunTujie/js/epub.min.map
ChanzhongshuochanJishuLilunTujie/js/hooks.min.js
ChanzhongshuochanJishuLilunTujie/js/hooks.min.map
ChanzhongshuochanJishuLilunTujie/js/reader.js
ChanzhongshuochanJishuLilunTujie/js/reader.js.map
ChanzhongshuochanJishuLilunTujie/js/reader.min.js
ChanzhongshuochanJishuLilunTujie/js/reader.min.map
ChanzhongshuochanJishuLilunTujie/js/hooks/__init__.py
chanzhongshuochan_jishu_lilun_tujie-2022.10.15.0.dist-info/METADATA
chanzhongshuochan_jishu_lilun_tujie-2022.10.15.0.dist-info/WHEEL
chanzhongshuochan_jishu_lilun_tujie-2022.10.15.0.dist-info/entry_points.txt
chanzhongshuochan_jishu_lilun_tujie-2022.10.15.0.dist-info/top_level.txt
chanzhongshuochan_jishu_lilun_tujie-2022.10.15.0.dist-info/RECORD
